{
  "fetchedAt": "2026-07-08T23:38:32+00:00",
  "samplingDurationSec": 480,
  "totalTankersInRegion": 11,
  "japanBoundTankers": 4,
  "japanBoundUnknownPort": 3,
  "topDestinationPorts": [
    {
      "port": "KAWASAKI",
      "count": 1
    }
  ],
  "vessels": [
    {
      "mmsi": 440103020,
      "name": "98CHEONGHAE",
      "destination": "",
      "isJapanBound": false,
      "lat": 35.0958,
      "lon": 129.0369
    },
    {
      "mmsi": 431024158,
      "name": "MIYA MARU NO.18",
      "destination": "JP WAK",
      "isJapanBound": true,
      "lat": 34.1468,
      "lon": 135.1903
    },
    {
      "mmsi": 440112380,
      "name": "KUKDONG3HO",
      "destination": "",
      "isJapanBound": false,
      "lat": 35.0606,
      "lon": 129.0456
    },
    {
      "mmsi": 440156960,
      "name": "SUNGJIN ACE",
      "destination": "",
      "isJapanBound": false,
      "lat": null,
      "lon": null
    },
    {
      "mmsi": 431501712,
      "name": "HASSHO MARU NO.1",
      "destination": ">JP KWS DU ENEOS 200",
      "isJapanBound": true,
      "lat": 35.4999,
      "lon": 139.7408
    },
    {
      "mmsi": 440105720,
      "name": "DAE JEONG",
      "destination": "BUSAN",
      "isJapanBound": false,
      "lat": 35.1226,
      "lon": 129.0518
    },
    {
      "mmsi": 440113630,
      "name": "WOOJIN1HO",
      "destination": "0",
      "isJapanBound": false,
      "lat": 35.1238,
      "lon": 129.0551
    },
    {
      "mmsi": 440072080,
      "name": "DL RUBY",
      "destination": "PUS,KR",
      "isJapanBound": false,
      "lat": 34.9539,
      "lon": 129.1118
    },
    {
      "mmsi": 431015453,
      "name": "MARUOKA MARU",
      "destination": "JP WAK OFF",
      "isJapanBound": true,
      "lat": 34.2079,
      "lon": 135.1208
    },
    {
      "mmsi": 431501701,
      "name": "ASAHI MARU",
      "destination": ">JP TYO HANEDA A",
      "isJapanBound": true,
      "lat": 35.5195,
      "lon": 139.7998
    },
    {
      "mmsi": 440206050,
      "name": "BUKWANG NO 5",
      "destination": "",
      "isJapanBound": false,
      "lat": null,
      "lon": null
    }
  ],
  "boundingBox": "24-46N / 122-146E",
  "source": "aisstream.io"
}
