{
  "fetchedAt": "2026-06-08T03:33:47+00:00",
  "samplingDurationSec": 480,
  "totalTankersInRegion": 23,
  "japanBoundTankers": 0,
  "japanBoundUnknownPort": 0,
  "topDestinationPorts": [],
  "vessels": [
    {
      "mmsi": 440410930,
      "name": "CHARIS",
      "destination": "BUSAN",
      "isJapanBound": false,
      "lat": 35.0972,
      "lon": 129.0781
    },
    {
      "mmsi": 440156960,
      "name": "SUNGJIN ACE",
      "destination": "",
      "isJapanBound": false,
      "lat": 35.1076,
      "lon": 129.0651
    },
    {
      "mmsi": 440130480,
      "name": "STELLA HO",
      "destination": "ULSAN",
      "isJapanBound": false,
      "lat": 35.122,
      "lon": 129.0522
    },
    {
      "mmsi": 440110880,
      "name": "2 SEUNG HAN",
      "destination": "",
      "isJapanBound": false,
      "lat": 35.1148,
      "lon": 129.0604
    },
    {
      "mmsi": 538011793,
      "name": "GEM LAYLA",
      "destination": "KR BNP",
      "isJapanBound": false,
      "lat": 34.997,
      "lon": 129.04
    },
    {
      "mmsi": 440115430,
      "name": "TAHITI",
      "destination": "BUSAN",
      "isJapanBound": false,
      "lat": 35.1226,
      "lon": 129.0516
    },
    {
      "mmsi": 538011933,
      "name": "SKY BLUE",
      "destination": "SGSIN",
      "isJapanBound": false,
      "lat": 33.2585,
      "lon": 127.9265
    },
    {
      "mmsi": 441450000,
      "name": "C. CHALLENGER",
      "destination": "KRGJE",
      "isJapanBound": false,
      "lat": 34.6233,
      "lon": 129.0528
    },
    {
      "mmsi": 440149350,
      "name": "NO.11 SEYANG",
      "destination": "BUSAN",
      "isJapanBound": false,
      "lat": 35.1002,
      "lon": 129.0898
    },
    {
      "mmsi": 273419360,
      "name": "OSTROV SAKHALIN",
      "destination": "VVO RUS",
      "isJapanBound": false,
      "lat": 33.0815,
      "lon": 127.7793
    },
    {
      "mmsi": 613419802,
      "name": "ASCENDANT",
      "destination": "KR_PUS",
      "isJapanBound": false,
      "lat": 35.0307,
      "lon": 129.0505
    },
    {
      "mmsi": 440027000,
      "name": "KEOYOUNG BLUE 1",
      "destination": "KR PUS",
      "isJapanBound": false,
      "lat": 35.0877,
      "lon": 129.0877
    },
    {
      "mmsi": 440400010,
      "name": "PHOENIX",
      "destination": "BUSAN",
      "isJapanBound": false,
      "lat": 35.1015,
      "lon": 129.0737
    },
    {
      "mmsi": 412474590,
      "name": "BAO RUN",
      "destination": "ULSAN",
      "isJapanBound": false,
      "lat": 35.0579,
      "lon": 129.2828
    },
    {
      "mmsi": 440103440,
      "name": "A-ONE",
      "destination": "BUSAN",
      "isJapanBound": false,
      "lat": 35.1199,
      "lon": 129.0504
    },
    {
      "mmsi": 440215590,
      "name": "DONGNAM ACE",
      "destination": "ULSAN",
      "isJapanBound": false,
      "lat": 35.1195,
      "lon": 129.051
    },
    {
      "mmsi": 353465000,
      "name": "BUENA DIOSA",
      "destination": "KR PUS",
      "isJapanBound": false,
      "lat": 35.0491,
      "lon": 129.0636
    },
    {
      "mmsi": 440194890,
      "name": "KS HONOR",
      "destination": "KR PUS",
      "isJapanBound": false,
      "lat": 35.054,
      "lon": 129.0395
    },
    {
      "mmsi": 441361000,
      "name": "YN OCEAN",
      "destination": "KR PUS",
      "isJapanBound": false,
      "lat": null,
      "lon": null
    },
    {
      "mmsi": 440113630,
      "name": "WOOJIN1HO",
      "destination": "0",
      "isJapanBound": false,
      "lat": 35.1239,
      "lon": 129.0552
    },
    {
      "mmsi": 440507780,
      "name": "23 BU GWANG",
      "destination": "BUSAN",
      "isJapanBound": false,
      "lat": 35.1056,
      "lon": 129.0904
    },
    {
      "mmsi": 440130790,
      "name": "7 MIREU",
      "destination": "",
      "isJapanBound": false,
      "lat": 35.1222,
      "lon": 129.0518
    },
    {
      "mmsi": 440154950,
      "name": "DONGJIN ACE",
      "destination": "BUSAN",
      "isJapanBound": false,
      "lat": 35.1211,
      "lon": 129.0504
    }
  ],
  "boundingBox": "24-46N / 122-146E",
  "source": "aisstream.io"
}
